aiamplitudes_common_public/__init__.py
aiamplitudes_common_public/_version.py
aiamplitudes_common_public/commonclasses.py
aiamplitudes_common_public/download_data.py
aiamplitudes_common_public/fbspaces.py
aiamplitudes_common_public/file_readers.py
aiamplitudes_common_public/polynomial_utils.py
aiamplitudes_common_public/preprocessing.py
aiamplitudes_common_public/rels_utils.py
aiamplitudes_common_public-1.2.1.dist-info/METADATA
aiamplitudes_common_public-1.2.1.dist-info/WHEEL
aiamplitudes_common_public-1.2.1.dist-info/licenses/LICENSE
aiamplitudes_common_public-1.2.1.dist-info/RECORD
