Metadata-Version: 2.4
Name: aiamplitudes-common-public
Version: 1.2.1
Summary: A library of common utils for the AI Amplitudes project
Project-URL: Homepage, https://github.com/AIAmplitudes
Author-email: Garrett Merz <garrett.merz@wisc.edu>, Francois Charton <fcharton@meta.com>, Tianji Cai <tianjiresearch@gmail.com>, Kyle Cranmer <kscranmer@wisc.edu>, Matthias Wilhelm <mailmwilhelm@imada.sdu.dk>, Lance Dixon <lance@slac.stanford.edu>
License: 
License-File: LICENSE
Classifier: License :: OSI Approved :: Apache Software License
Classifier: Operating System :: OS Independent
Classifier: Programming Language :: Python :: 3
Requires-Python: >=3.10
Requires-Dist: beautifulsoup4>=4.0.0
Requires-Dist: einops>=0.7.0
Requires-Dist: matplotlib>=3.7.1
Requires-Dist: numpy>=1.24.1
Requires-Dist: pandas>=2.0.3
Requires-Dist: scipy>=1.10.1
Requires-Dist: tensorboard>=2.12.3
Requires-Dist: torch>=2.8.0
Requires-Dist: torchaudio>=2.8.0
Requires-Dist: torchmetrics>=1.6.0
Requires-Dist: torchvision>=0.23.0
Requires-Dist: wandb>=0.15.8
